sibc/__init__.py
sibc/__main__.py
sibc/common.py
sibc/constants.py
sibc/fauxoo.py
sibc/math.py
sibc/plot_strategy.py
sibc/polymul.py
sibc/polyredc.py
sibc/precompute_sdacs.py
sibc/primefield.py
sibc/quadraticfield.py
sibc/timing.py
sibc/bsidh/__init__.py
sibc/bsidh/main.py
sibc/bsidh/precompute_parameters.py
sibc/bsidh/precompute_strategy.py
sibc/bsidh/strategy.py
sibc/bsidh/test.py
sibc/csidh/__init__.py
sibc/csidh/bench.py
sibc/csidh/bounds.py
sibc/csidh/gae_df.py
sibc/csidh/gae_wd1.py
sibc/csidh/gae_wd2.py
sibc/csidh/header.py
sibc/csidh/ijk.py
sibc/csidh/main.py
sibc/csidh/precompute_parameters.py
sibc/csidh/precompute_strategy.py
sibc/csidh/sdacs.py
sibc/csidh/test.py
sibc/data/exponents/mitm/128/df/e1
sibc/data/exponents/mitm/128/df/e10
sibc/data/exponents/mitm/128/df/e2
sibc/data/exponents/mitm/128/df/e3
sibc/data/exponents/mitm/128/wd1/e1
sibc/data/exponents/mitm/128/wd1/e10
sibc/data/exponents/mitm/128/wd1/e2
sibc/data/exponents/mitm/128/wd1/e3
sibc/data/exponents/mitm/128/wd2/e1
sibc/data/exponents/mitm/128/wd2/e2
sibc/data/exponents/mitm/128/wd2/e5
sibc/data/exponents/mitm/192/df/e1
sibc/data/exponents/mitm/192/wd1/e1
sibc/data/exponents/mitm/192/wd2/e1
sibc/data/exponents/vow-gcs/128/df/e1
sibc/data/exponents/vow-gcs/128/wd1/e1
sibc/data/exponents/vow-gcs/128/wd2/e1
sibc/data/exponents/vow-gcs/192/df/e1
sibc/data/exponents/vow-gcs/192/wd1/e1
sibc/data/exponents/vow-gcs/192/wd2/e1
sibc/data/gen/montgomery/b2
sibc/data/gen/montgomery/b3
sibc/data/gen/montgomery/b5
sibc/data/gen/montgomery/b6
sibc/data/gen/montgomery/s1
sibc/data/ijk/montgomery/b2-scaled
sibc/data/ijk/montgomery/b2-unscaled
sibc/data/ijk/montgomery/b3-scaled
sibc/data/ijk/montgomery/b3-unscaled
sibc/data/ijk/montgomery/b5-scaled
sibc/data/ijk/montgomery/b5-unscaled
sibc/data/ijk/montgomery/b6-scaled
sibc/data/ijk/montgomery/b6-unscaled
sibc/data/ijk/montgomery/p1024-scaled
sibc/data/ijk/montgomery/p1024-unscaled
sibc/data/ijk/montgomery/p1792-scaled
sibc/data/ijk/montgomery/p1792-unscaled
sibc-0.0.1.dist-info/LICENSE
sibc-0.0.1.dist-info/METADATA
sibc-0.0.1.dist-info/WHEEL
sibc-0.0.1.dist-info/entry_points.txt
sibc-0.0.1.dist-info/top_level.txt
sibc-0.0.1.dist-info/RECORD
