Metadata-Version: 2.1
Name: sibc
Version: 0.0.1
Summary: Supersingular Isogeny-Based Cryptography constructions: currently, csidh and bsidh are implemented by using traditional and velusqrt formulae on Montgomery curve x-only projective coordinates
Home-page: https://github.com/JJChiDguez/sibc
Author: JJChiDguez
Author-email: chidoys@gmail.com
License: GPLv3
Keywords: csidh,bsidh,sibc,encryption
Platform: UNKNOWN
Classifier: Programming Language :: Python :: 3
Classifier: License :: OSI Approved :: GNU General Public License v3 (GPLv3)
Classifier: Operating System :: OS Independent
Requires-Python: >=3.7
Requires-Dist: click
Requires-Dist: matplotlib
Requires-Dist: networkx
Requires-Dist: numpy
Requires-Dist: progress
